README.txt
setup.cfg
setup.py
svnignore.sh
version.txt
docs/HISTORY.txt
docs/INSTALL.txt
docs/LICENSE.GPL
docs/LICENSE.txt
src/collective/__init__.py
src/collective.portlet.localcumulus.egg-info/PKG-INFO
src/collective.portlet.localcumulus.egg-info/SOURCES.txt
src/collective.portlet.localcumulus.egg-info/dependency_links.txt
src/collective.portlet.localcumulus.egg-info/entry_points.txt
src/collective.portlet.localcumulus.egg-info/namespace_packages.txt
src/collective.portlet.localcumulus.egg-info/requires.txt
src/collective.portlet.localcumulus.egg-info/top_level.txt
src/collective/portlet/__init__.py
src/collective/portlet/localcumulus/__init__.py
src/collective/portlet/localcumulus/app_config.py
src/collective/portlet/localcumulus/catalog.py
src/collective/portlet/localcumulus/configure.zcml
src/collective/portlet/localcumulus/cumulusportlet.pt
src/collective/portlet/localcumulus/interfaces.py
src/collective/portlet/localcumulus/localcumulus.py
src/collective/portlet/localcumulus/portlet.py
src/collective/portlet/localcumulus/rebuild_i18n.sh
src/collective/portlet/localcumulus/setuphandlers.py
src/collective/portlet/localcumulus/version.txt
src/collective/portlet/localcumulus/Extensions/Install.py
src/collective/portlet/localcumulus/Extensions/__init__.py
src/collective/portlet/localcumulus/locales/collective.portlet.localcumulus-manual.pot
src/collective/portlet/localcumulus/locales/collective.portlet.localcumulus.pot
src/collective/portlet/localcumulus/locales/fr/LC_MESSAGES/collective.portlet.localcumulus.po
src/collective/portlet/localcumulus/profiles/default/collective.portlet.localcumulus_various.txt
src/collective/portlet/localcumulus/profiles/default/import_steps.xml
src/collective/portlet/localcumulus/profiles/default/portlets.xml
src/collective/portlet/localcumulus/tests/__init__.py
src/collective/portlet/localcumulus/tests/base.py
src/collective/portlet/localcumulus/tests/custom.txt
src/collective/portlet/localcumulus/tests/globals.py
src/collective/portlet/localcumulus/tests/renderer.txt
src/collective/portlet/localcumulus/tests/suite.py
src/collective/portlet/localcumulus/tests/test_customportlet.py
src/collective/portlet/localcumulus/tests/test_doctests.py
src/collective/portlet/localcumulus/tests/test_portlet.py
src/collective/portlet/localcumulus/tests/testing.cfg
src/collective/portlet/localcumulus/tests/user_globals.py