Metadata-Version: 1.0
Name: collective.portlet.localcumulus
Version: 1.4
Summary: Project collective.portlet.localcumulus cumulus product
Home-page: http://pypi.python.org/pypi/collective.portlet.localcumulus
Author: kiorky
Author-email: kiorky@cryptelium.net
License: GPL
Platform: UNKNOWN
Classifier: Programming Language :: Python
Classifier: Topic :: Software Development
